{
    "100": " Bulgaria/保加利亚",
    "104": " Myanmar (Burma)/缅甸",
    "108": " Burundi/布隆迪",
    "112": " Belarus/白俄罗斯",
    "116": " Cambodia/柬埔寨",
    "120": " Cameroon/喀麦隆",
    "124": " Canada/加拿大",
    "132": " Cape-Verde/佛得角",
    "136": " Cayman Islands/开曼群岛",
    "140": " Central-African-Republic/中非",
    "144": " Sri Lanka/斯里兰卡",
    "148": " Chad/乍得",
    "152": " Chile/智利",
    "156": " China/中国",
    "158": "Taiwan/中华民国（台湾）",
    "162": " Christmas-Island/圣诞岛",
    "166": " Cocos-(Keeling)-Islands/科科斯群岛",
    "170": " Colombia/哥伦比亚",
    "174": " The Comoros/科摩罗",
    "175": " Mayotte/马约特",
    "178": " Republic-of-the-Congo/刚果（布）",
    "180": " Democratic-Republic-of-the-Congo/刚果（金）",
    "184": " Cook-Islands/库克群岛",
    "188": " Costa-Rica/哥斯达黎加",
    "191": " Croatia/克罗地亚",
    "192": " Cuba/古巴",
    "196": " Cyprus/塞浦路斯",
    "203": " Czech-Republic/捷克",
    "204": " Benin/贝宁",
    "208": " Denmark/丹麦",
    "212": " Dominica/多米尼克",
    "214": " Dominican-Republic/多米尼加",
    "218": " Ecuador/厄瓜多尔",
    "222": " El Salvador/萨尔瓦多",
    "226": " Equatorial Guinea/赤道几内亚",
    "231": " Ethiopia/埃塞俄比亚",
    "232": " Eritrea/厄立特里亚",
    "233": " Estonia/爱沙尼亚",
    "234": " Faroe Islands/法罗群岛",
    "238": " Falkland-Islands/马尔维纳斯群岛（福克兰）",
    "239": " South Georgia and the South Sandwich Islands/南乔治亚岛和南桑威奇群岛",
    "242": " Fiji/斐济群岛",
    "246": " Finland/芬兰",
    "248": " Åaland-Island/奥兰群岛",
    "250": " France/法国",
    "254": " French Guiana/法属圭亚那",
    "258": " French polynesia/法属波利尼西亚",
    "260": " French Southern Territories/法属南部领地",
    "262": " Djibouti/吉布提",
    "266": " Gabon/加蓬",
    "268": " Georgia/格鲁吉亚",
    "270": " Gambia/冈比亚",
    "275": " Palestinian territories/巴勒斯坦",
    "276": " Germany/德国",
    "288": " Ghana/加纳",
    "292": " Gibraltar/直布罗陀",
    "296": " Kiribati/基里巴斯",
    "300": " Greece/希腊",
    "304": " Greenland/格陵兰",
    "308": " Grenada/格林纳达",
    "312": " Guadeloupe/瓜德罗普",
    "316": " Guam/关岛",
    "320": " Guatemala/危地马拉",
    "324": " Guinea/几内亚",
    "328": " Guyana/圭亚那",
    "332": " Haiti/海地",
    "334": " Heard Island and McDonald Islands/赫德岛和麦克唐纳群岛",
    "336": " Vatican City (The Holy See)/梵蒂冈",
    "340": " Honduras/洪都拉斯",
    "344": " Hong Kong/香港",
    "348": " Hungary/匈牙利",
    "352": " Iceland/冰岛",
    "356": " India/印度",
    "360": " Indonesia/印尼",
    "364": " Iran/伊朗",
    "368": " Iraq/伊拉克",
    "372": " Ireland/爱尔兰",
    "376": " Israel/以色列",
    "380": " Italy/意大利",
    "384": " Côte-d'Ivoire/科特迪瓦",
    "388": " Jamaica/牙买加",
    "392": " Japan/日本",
    "398": " Kazakhstan/哈萨克斯坦",
    "400": " Jordan/约旦",
    "404": " Kenya/肯尼亚",
    "408": " North Korea/朝鲜",
    "410": " South Korea/韩国",
    "414": " Kuwait/科威特",
    "417": " Kyrgyzstan/吉尔吉斯斯坦",
    "418": " Laos/老挝",
    "422": " Lebanon/黎巴嫩",
    "426": " Lesotho/莱索托",
    "428": " Latvia/拉脱维亚",
    "430": " Liberia/利比里亚",
    "434": " Libya/利比亚",
    "438": " Liechtenstein/列支敦士登",
    "440": " Lithuania/立陶宛",
    "442": " Luxembourg/卢森堡",
    "446": " Macao/澳门",
    "450": " Madagascar/马达加斯加",
    "454": " Malawi/马拉维",
    "458": " Malaysia/马来西亚",
    "462": " Maldives/马尔代夫",
    "466": " Mali/马里",
    "470": " Malta/马耳他",
    "474": " Martinique/马提尼克",
    "478": " Mauritania/毛里塔尼亚",
    "480": " Mauritius/毛里求斯",
    "484": " Mexico/墨西哥",
    "492": " Monaco/摩纳哥",
    "496": " Mongolia/蒙古",
    "498": " Moldova/摩尔多瓦",
    "499": " Montenegro/黑山",
    "500": " Montserrat/蒙塞拉特岛",
    "504": " Morocco/摩洛哥",
    "508": " Mozambique/莫桑比克",
    "512": " Oman/阿曼",
    "516": " Namibia/纳米比亚",
    "520": " Nauru/瑙鲁",
    "524": " Nepal/尼泊尔",
    "528": " Netherlands/荷兰",
    "533": " Aruba/阿鲁巴",
    "535": " Caribbean-Netherlands/荷兰加勒比区",
    "540": " New Caledonia/新喀里多尼亚",
    "548": " Vanuatu/瓦努阿图",
    "554": " New Zealand/新西兰",
    "558": " Nicaragua/尼加拉瓜",
    "562": " Niger/尼日尔",
    "566": " Nigeria/尼日利亚",
    "570": " Niue/纽埃",
    "574": " Norfolk Island/诺福克岛",
    "578": " Norway/挪威",
    "580": " Northern Mariana Islands/北马里亚纳群岛",
    "581": " United States Minor Outlying Islands/美国本土外小岛屿",
    "583": " Federated-States-of-Micronesia/密克罗尼西亚联邦",
    "584": " Marshall islands/马绍尔群岛",
    "585": " Palau/帕劳",
    "586": " Pakistan/巴基斯坦",
    "591": " Panama/巴拿马",
    "598": " Papua New Guinea/巴布亚新几内亚",
    "600": " Paraguay/巴拉圭",
    "604": " Peru/秘鲁",
    "608": " The Philippines/菲律宾",
    "612": " Pitcairn Islands/皮特凯恩群岛",
    "616": " Poland/波兰",
    "620": " Portugal/葡萄牙",
    "624": " Guinea-Bissau/几内亚比绍",
    "626": " Timor-Leste (East Timor)/东帝汶",
    "630": " Puerto Rico/波多黎各",
    "634": " Qatar/卡塔尔",
    "638": " Réunion/留尼汪",
    "642": " Romania/罗马尼亚",
    "643": " Russian Federation/俄罗斯",
    "646": " Rwanda/卢旺达",
    "652": " Saint-Barthélemy/圣巴泰勒米岛",
    "654": " St. Helena & Dependencies/圣赫勒拿",
    "659": " St. Kitts & Nevis/圣基茨和尼维斯",
    "660": " Anguilla/安圭拉",
    "662": " St. Lucia/圣卢西亚",
    "663": " Saint Martin (France)/法属圣马丁",
    "666": " Saint-Pierre and Miquelon/圣皮埃尔和密克隆",
    "670": " St. Vincent & the Grenadines/圣文森特和格林纳丁斯",
    "674": " San Marino/圣马力诺",
    "678": " Sao Tome & Principe/圣多美和普林西比",
    "682": " Saudi Arabia/沙特阿拉伯",
    "686": " Senegal/塞内加尔",
    "688": " Serbia/塞尔维亚",
    "690": " Seychelles/塞舌尔",
    "694": " Sierra Leone/塞拉利昂",
    "702": " Singapore/新加坡",
    "703": " Slovakia/斯洛伐克",
    "704": " Vietnam/越南",
    "705": " Slovenia/斯洛文尼亚",
    "706": " Somalia/索马里",
    "710": " South Africa/南非",
    "716": " Zimbabwe/津巴布韦",
    "724": " Spain/西班牙",
    "728": " South Sudan/南苏丹",
    "729": " Sudan/苏丹",
    "732": " Western-Sahara/西撒哈拉",
    "740": " Suriname/苏里南",
    "744": "Template:Country data SJM Svalbard/斯瓦尔巴群岛和扬马延岛",
    "748": " Swaziland/斯威士兰",
    "752": " Sweden/瑞典",
    "756": " Switzerland/瑞士",
    "760": " Syria/叙利亚",
    "762": " Tajikistan/塔吉克斯坦",
    "764": " Thailand/泰国",
    "768": " Togo/多哥",
    "772": " Tokelau/托克劳",
    "776": " Tonga/汤加",
    "780": " Trinidad & Tobago/特立尼达和多巴哥",
    "784": " United-Arab-Emirates/阿联酋",
    "788": " Tunisia/突尼斯",
    "792": " Turkey/土耳其",
    "795": " Turkmenistan/土库曼斯坦",
    "796": " Turks & Caicos Islands/特克斯和凯科斯群岛",
    "798": " Tuvalu/图瓦卢",
    "800": " Uganda/乌干达",
    "804": " Ukraine/乌克兰",
    "807": " Republic of Macedonia (FYROM)/马其顿",
    "818": " Egypt/埃及",
    "826": " Great Britain (United Kingdom; England)/英国",
    "831": " Guernsey/根西岛",
    "832": " Jersey/泽西岛",
    "833": " Isle of Man/马恩岛",
    "834": " Tanzania/坦桑尼亚",
    "840": " United States of America (USA)/美国",
    "850": " United States Virgin Islands/美属维尔京群岛",
    "854": " Burkina/布基纳法索",
    "858": " Uruguay/乌拉圭",
    "860": " Uzbekistan/乌兹别克斯坦",
    "862": " Venezuela/委内瑞拉",
    "876": " Wallis and Futuna/瓦利斯和富图纳",
    "882": " Samoa/萨摩亚",
    "887": " Yemen/也门",
    "894": " Zambia/赞比亚",
    "020": " Andorra/安道尔",
    "004": " Afghanistan/阿富汗",
    "028": " Antigua-&-Barbuda/安提瓜和巴布达",
    "008": " Albania/阿尔巴尼亚",
    "051": " Armenia/亚美尼亚",
    "024": " Angola/安哥拉",
    "010": " Antarctica/南极洲",
    "032": " Argentina/阿根廷",
    "016": " American-Samoa/美属萨摩亚",
    "040": " Austria/奥地利",
    "036": " Australia/澳大利亚",
    "031": " Azerbaijan/阿塞拜疆",
    "070": " Bosnia-&-Herzegovina/波黑",
    "052": " Barbados/巴巴多斯",
    "050": " Bangladesh/孟加拉",
    "056": " Belgium/比利时",
    "048": " Bahrain/巴林",
    "060": " Bermuda/百慕大",
    "096": " Brunei/文莱",
    "068": " Bolivia/玻利维亚",
    "076": " Brazil/巴西",
    "044": " The-Bahamas/巴哈马",
    "064": " Bhutan/不丹",
    "074": " Bouvet-Island/布韦岛",
    "072": " Botswana/博茨瓦纳",
    "084": " Belize/伯利兹",
    "012": " Algeria/阿尔及利亚",
    "086": " British Indian Ocean Territory/英属印度洋领地",
    "090": " Solomon Islands/所罗门群岛",
    "092": " British Virgin Islands/英属维尔京群岛"
}